AmazonASINMatcher/Check_Url.py
AmazonASINMatcher/Check_pattern.py
AmazonASINMatcher/Link.py
AmazonASINMatcher/Link_object.py
AmazonASINMatcher/Region.py
AmazonASINMatcher/__init__.py
AmazonASINMatcher-3.2.dist-info/LICENSE.txt
AmazonASINMatcher-3.2.dist-info/METADATA
AmazonASINMatcher-3.2.dist-info/RECORD
AmazonASINMatcher-3.2.dist-info/WHEEL
AmazonASINMatcher-3.2.dist-info/top_level.txt
