Metadata-Version: 2.1
Name: AmazonASINMatcher
Version: 3.2
Summary: A project to get the product details on Amazon
Home-page: https://github.com/reetikaSR/AmazonASINMatcher
Author: reetikaS
License: UNKNOWN
Platform: UNKNOWN
Classifier: Programming Language :: Python :: 3.6
Classifier: License :: OSI Approved :: MIT License
